sketching/__init__.py
sketching/abstracted.py
sketching/bezier_util.py
sketching/const.py
sketching/control_struct.py
sketching/data_struct.py
sketching/geo.py
sketching/local_data_struct.py
sketching/pillow_util.py
sketching/py.typed
sketching/shape_struct.py
sketching/sketch2d_keymap.py
sketching/sketch2dapp.py
sketching/sketch2dstatic.py
sketching/sketch2dweb.py
sketching/state_struct.py
sketching/transform.py
sketching/test/IBMPlexMono-Regular.ttf
sketching/test/__init__.py
sketching/test/test_abstracted.py
sketching/test/test_bezier_util.py
sketching/test/test_control_struct.py
sketching/test/test_geo.py
sketching/test/test_local_data_struct.py
sketching/test/test_pillow_util.py
sketching/test/test_shape_struct.py
sketching/test/test_sketch2d_keymap.py
sketching/test/test_state_struct.py
sketching/test/test_transform.py
sketching-0.0.8.dist-info/METADATA
sketching-0.0.8.dist-info/WHEEL
sketching-0.0.8.dist-info/licenses/LICENSE.md
sketching-0.0.8.dist-info/RECORD
