Metadata-Version: 2.1
Name: sketching
Version: 0.0.8
Summary: Tools for quick creative programmig.
Project-URL: Homepage, https://sketchingpy.org
Project-URL: Documentation, https://sketchingpy.org/reference
Project-URL: Source, https://codeberg.org/sketching/Sketchingpy
Project-URL: Issue Tracker, https://codeberg.org/sketching/Sketchingpy/issues
Project-URL: Changelog, https://codeberg.org/sketching/Sketchingpy/commits/branch/main
Author-email: A Samuel Pottinger <hello@sketchingpy.org>
License-File: LICENSE.md
Classifier: Development Status :: 2 - Pre-Alpha
Classifier: License :: OSI Approved :: BSD License
Classifier: Operating System :: OS Independent
Classifier: Programming Language :: Python :: 3
Classifier: Topic :: Games/Entertainment
Classifier: Topic :: Multimedia
Classifier: Topic :: Multimedia :: Graphics
Classifier: Topic :: Scientific/Engineering :: Visualization
Requires-Python: >=3.7
Provides-Extra: desktop
Requires-Dist: bezier~=2023.7.28; extra == 'desktop'
Requires-Dist: matplotlib~=3.8.2; extra == 'desktop'
Requires-Dist: numpy~=1.26.2; extra == 'desktop'
Requires-Dist: pillow~=10.1.0; extra == 'desktop'
Requires-Dist: pygame~=2.5.2; extra == 'desktop'
Provides-Extra: dev
Requires-Dist: bezier~=2023.7.28; extra == 'dev'
Requires-Dist: jinja2~=3.1.2; extra == 'dev'
Requires-Dist: mypy~=1.8.0; extra == 'dev'
Requires-Dist: nose2~=0.14.0; extra == 'dev'
Requires-Dist: pycodestyle~=2.11.1; extra == 'dev'
Requires-Dist: pyflakes~=3.1.0; extra == 'dev'
Requires-Dist: pyyaml~=6.0.1; extra == 'dev'
Requires-Dist: selenium~=4.16.0; extra == 'dev'
Requires-Dist: types-pillow~=10.1.0.2; extra == 'dev'
Provides-Extra: minimal
Requires-Dist: pillow~=10.1.0; extra == 'minimal'
Provides-Extra: notebook
Requires-Dist: bezier~=2023.7.28; extra == 'notebook'
Requires-Dist: matplotlib~=3.8.2; extra == 'notebook'
Requires-Dist: numpy~=1.26.2; extra == 'notebook'
Requires-Dist: pillow~=10.1.0; extra == 'notebook'
Provides-Extra: static
Requires-Dist: bezier~=2023.7.28; extra == 'static'
Requires-Dist: matplotlib~=3.8.2; extra == 'static'
Requires-Dist: numpy~=1.26.2; extra == 'static'
Requires-Dist: pillow~=10.1.0; extra == 'static'
